retentive_network/__init__.py
retentive_network/exceptions.py
retentive_network/layers/__init__.py
retentive_network/layers/feed_forward.py
retentive_network/layers/group_norm.py
retentive_network/layers/layer_norm.py
retentive_network/layers/multi_scale_retention.py
retentive_network/layers/projection.py
retentive_network/layers/retention.py
retentive_network/layers/swish_gate.py
retentive_network/models/__init__.py
retentive_network/models/clm.py
retentive_network/models/network.py
retentive_network-0.1.0.dist-info/LICENSE
retentive_network-0.1.0.dist-info/METADATA
retentive_network-0.1.0.dist-info/WHEEL
retentive_network-0.1.0.dist-info/RECORD
